llm_drift_ctl/__init__.py
llm_drift_ctl/baseline.py
llm_drift_ctl/cloud.py
llm_drift_ctl/content.py
llm_drift_ctl/drift_guard.py
llm_drift_ctl/format.py
llm_drift_ctl/types.py
llm_drift_ctl/adapters/__init__.py
llm_drift_ctl/adapters/openai_adapter.py
llm_drift_ctl-0.1.2.dist-info/METADATA
llm_drift_ctl-0.1.2.dist-info/WHEEL
llm_drift_ctl-0.1.2.dist-info/top_level.txt
llm_drift_ctl-0.1.2.dist-info/RECORD
