Metadata-Version: 2.4
Name: llm-drift-ctl
Version: 0.1.2
Summary: Production-grade LLM output validation package. Validates LLM outputs using your own LLM when needed — and no LLM when not.
Author: llm-drift-ctl
License: MIT
Keywords: llm,validation,drift,quality,guard
Classifier: Development Status :: 3 - Alpha
Classifier: Intended Audience :: Developers
Classifier: License :: OSI Approved :: MIT License
Classifier: Programming Language :: Python :: 3
Classifier: Programming Language :: Python :: 3.8
Classifier: Programming Language :: Python :: 3.9
Classifier: Programming Language :: Python :: 3.10
Classifier: Programming Language :: Python :: 3.11
Requires-Python: >=3.8
Requires-Dist: aiohttp>=3.8.0
Provides-Extra: dev
Requires-Dist: pytest>=7.0.0; extra == "dev"
Requires-Dist: pytest-asyncio>=0.21.0; extra == "dev"
